sphinx_inline_svg/__init__.py
sphinx_inline_svg/inline_svg.py
sphinx_inline_svg-0.2.0.dist-info/METADATA
sphinx_inline_svg-0.2.0.dist-info/WHEEL
sphinx_inline_svg-0.2.0.dist-info/licenses/LICENSE
sphinx_inline_svg-0.2.0.dist-info/RECORD
