Metadata-Version: 2.3
Name: sphinx-inline-svg
Version: 0.2.0
Summary: Sphinx extension to make svg images inline
Project-URL: Homepage, https://github.com/satamame/sphinx-inline-svg
Project-URL: Repository, https://github.com/satamame/sphinx-inline-svg.git
Project-URL: Issues, https://github.com/satamame/sphinx-inline-svg/issues
Project-URL: Changelog, https://github.com/satamame/sphinx-inline-svg/releases
Author-email: satamame <satamame@gmail.com>
License: MIT
License-File: LICENSE
Keywords: extension,inline,sphinx,svg
Classifier: Development Status :: 4 - Beta
Classifier: Framework :: Sphinx
Classifier: Framework :: Sphinx :: Extension
Classifier: License :: OSI Approved :: MIT License
Classifier: Programming Language :: Python :: 3
Requires-Python: >=3.9
Requires-Dist: lxml>=5.3.0
Requires-Dist: sphinx>=7.4.0
